job_offer_classifier/__init__.py
job_offer_classifier/_nbdev.py
job_offer_classifier/k_fold_validation.py
job_offer_classifier/merge_datasets.py
job_offer_classifier/multiclass.py
job_offer_classifier/pipeline_classifier.py
job_offer_classifier/validations.py
job_offer_classifier-0.0.8.dist-info/LICENSE
job_offer_classifier-0.0.8.dist-info/METADATA
job_offer_classifier-0.0.8.dist-info/WHEEL
job_offer_classifier-0.0.8.dist-info/entry_points.txt
job_offer_classifier-0.0.8.dist-info/top_level.txt
job_offer_classifier-0.0.8.dist-info/RECORD
