Metadata-Version: 2.1
Name: job-offer-classifier
Version: 0.0.8
Summary: Classification of Job Offer Responses
Home-page: https://github.com/kikejimenez/job_offer_classifier/tree/master/
Author: E Jimenez
Author-email: ejimenez@intekglobal.com
License: Apache Software License 2.0
Keywords: Machine Learning,Sentiment Analysis
Platform: UNKNOWN
Classifier: Development Status :: 3 - Alpha
Classifier: Intended Audience :: Developers
Classifier: License :: OSI Approved :: Apache Software License
Classifier: Natural Language :: English
Classifier: Programming Language :: Python :: 3.6
Classifier: Programming Language :: Python :: 3.7
Classifier: Programming Language :: Python :: 3.8
Requires-Python: >=3.6
Requires-Dist: tensorflow
Requires-Dist: tensorflow-hub
Requires-Dist: numpy
Requires-Dist: pandas
Requires-Dist: matplotlib
Requires-Dist: seaborn
Requires-Dist: mimesis
